yaqd_gage/VERSION
yaqd_gage/__init__.py
yaqd_gage/__version__.py
yaqd_gage/_chopping.py
yaqd_gage/_compuscope.py
yaqd_gage/_constants.py
yaqd_gage/_exceptions.py
yaqd_gage/_plot.py
yaqd_gage/_pygage.py
yaqd_gage/gage-chopping.avpr
yaqd_gage/gage-chopping.toml
yaqd_gage/gage-compuscope.avpr
yaqd_gage/gage-compuscope.toml
yaqd_gage/gui/_samples_gui.py
yaqd_gage/gui/_segments_gui.py
yaqd_gage-2026.1.0.dist-info/entry_points.txt
yaqd_gage-2026.1.0.dist-info/licenses/LICENSE
yaqd_gage-2026.1.0.dist-info/WHEEL
yaqd_gage-2026.1.0.dist-info/METADATA
yaqd_gage-2026.1.0.dist-info/RECORD
