Metadata-Version: 2.4
Name: yaqd-gage
Version: 2026.1.0
Summary: yaq daemons for GaGe hardware
Home-page: https://yaq.fyi
Author: yaq developers
Requires-Python: >=3.7
Classifier: Development Status :: 2 - Pre-Alpha
Classifier: Intended Audience :: Science/Research
Classifier: License :: OSI Approved :: GNU Lesser General Public License v3 (LGPLv3)
Classifier: Natural Language :: English
Classifier: Programming Language :: Python :: 3
Classifier: Programming Language :: Python :: 3.7
Classifier: Programming Language :: Python :: 3.8
Classifier: Topic :: Scientific/Engineering
License-File: LICENSE
Requires-Dist: yaqd-core>=2020.06.3
Requires-Dist: numpy
Requires-Dist: toml>=0.10.2
Requires-Dist: yaq-traits
Requires-Dist: qtypes
Requires-Dist: toml
Requires-Dist: black ; extra == "dev"
Requires-Dist: pre-commit ; extra == "dev"
Project-URL: Issues, https://github.com/yaq-project/yaqd-gage/issues
Project-URL: Source, https://github.com/yaq-project/yaqd-gage
Provides-Extra: dev
